{
    "redovna" : 
    [
        {   
            "dan" : "0",
            "semestar" : "Zimski",
            "pocetak" : "11:15", 
            "kraj" : "12:00", 
            "naziv" : "A1", 
            "predavac" : "Ban Kulin"
        },
        {   
            "dan" : "1",
            "semestar" : "Zimski",
            "pocetak" : "15:15", 
            "kraj" : "16:15", 
            "naziv" : "A1", 
            "predavac" : "Ban Kulin"
        },
        {   
            "dan" : "2",
            "semestar" : "Zimski",
            "pocetak" : "09:15", 
            "kraj" : "12:15", 
            "naziv" : "A2", 
            "predavac" : "Ban Kulin"
        },
        {   
            "dan" : "3",
            "semestar" : "Zimski",
            "pocetak" : "13:15", 
            "kraj" : "17:15", 
            "naziv" : "A2", 
            "predavac" : "Ban Kulin"
        }
    ],

    "vanredna" : 
    [
        {   
            "datum" : "23.11.2019",
            "pocetak" : "13:15", 
            "kraj" : "17:15", 
            "naziv" : "A1", 
            "predavac" : "Ban Kulin"
        },
        {   
            "datum" : "25.12.2019",
            "pocetak" : "13:15", 
            "kraj" : "17:15", 
            "naziv" : "A2", 
            "predavac" : "Ban Kulin"
        },
        {   
            "datum" : "23.12.2019",
            "pocetak" : "13:15", 
            "kraj" : "17:15", 
            "naziv" : "A1", 
            "predavac" : "Ban Kulin"
        },
        {   
            "datum" : "12.01.2020",
            "pocetak" : "13:15", 
            "kraj" : "17:15", 
            "naziv" : "A1", 
            "predavac" : "Ban Kulin"
        },
        {   
            "datum" : "01.12.2020",
            "pocetak" : "13:15", 
            "kraj" : "17:15", 
            "naziv" : "A1", 
            "predavac" : "Ban Kulin"
        },
        {   
            "datum" : "23.01.2020",
            "pocetak" : "13:15", 
            "kraj" : "17:15", 
            "naziv" : "A1", 
            "predavac" : "Ban Kulin"
        },
        {   
            "datum" : "23.01.2020",
            "pocetak" : "13:15", 
            "kraj" : "17:15", 
            "naziv" : "A2", 
            "predavac" : "Ban Kulin"
        }
    ]
}

